{
  "divisiones" : {
    "5MA" : {
      "43448188" : "Luciana_Skakovsky",
      "43448452" : "Andrés_Guinsburg",
      "43626546" : "Luciano_Garbarino",
      "43630178" : "Federico_Custeau",
      "43697812" : "Mateo_Stefanides",
      "43725334" : "Dan_Farach",
      "43819134" : "Kevin_Liao",
      "43819469" : "Tomas_Jais",
      "43874249" : "Federico_Galante",
      "43901510" : "Maximo_Estray",
      "43917960" : "Dan_Szujatovich",
      "43987841" : "Milena_Kuzminski_Sabato",
      "43992906" : "Gianfranco_Loayza",
      "44159009" : "Marcos_Parengo",
      "44159126" : "Leonel_Braginski"
    }
  },
  "día" : "jueves",
  "escaneado" : {
    "43448452" : 0,
    "43626546" : 0,
    "43630178" : 1,
    "43725334" : 0,
    "43819469" : 0,
    "43917960" : 0,
    "43992906" : 0,
    "44159126" : 0
  },
  "faltas" : {
    "5MA" : {
      "43448452" : {
        "Digitales" : 0,
        "PP" : 0
      },
      "43626546" : {
        "Digitales" : 0,
        "HRC" : 0,
        "PF" : 2,
        "PP" : 0,
        "Sistemas" : 1
      },
      "43630178" : {
        "PP" : 12
      },
      "43725334" : {
        "Digitales" : 0,
        "HRC" : 0,
        "PF" : 1,
        "PP" : 0,
        "Sistemas" : 1
      },
      "43819469" : {
        "Digitales" : 1,
        "PP" : 0
      },
      "43917960" : {
        "Digitales" : 2,
        "HRC" : 0,
        "PF" : 1,
        "PP" : 0,
        "Sistemas" : 1
      },
      "43992906" : {
        "Digitales" : 3,
        "HRC" : 0,
        "PF" : 1,
        "PP" : 0,
        "Sistemas" : 1
      },
      "44159126" : {
        "Analógica" : 21,
        "Digitales" : 5,
        "HRC" : 30,
        "PF" : 0,
        "PP" : 12,
        "Sistemas" : 16
      }
    }
  },
  "fecha" : "26/9",
  "hora" : "10:17:01",
  "horarios" : {
    "5MA" : {
      "jueves" : [ null, {
        "horario" : "7.45 / 9.05",
        "id" : "PP",
        "numero" : "1"
      }, {
        "horario" : "9.15 / 10.40",
        "id" : "PP",
        "numero" : "2"
      }, {
        "horario" : "10.50 / 12.15",
        "id" : "HRC",
        "numero" : "3"
      }, {
        "horario" : "13.10 / 14.30",
        "id" : "Ed. Fisica",
        "numero" : "4"
      }, {
        "horario" : "14.40 / 16.00",
        "id" : "Fuentes",
        "numero" : "5"
      }, {
        "horario" : "16.10 / 17.30",
        "id" : "Filosofia",
        "numero" : "6"
      } ],
      "lunes" : [ null, {
        "horario" : "7.45 / 9.05",
        "id" : "Quimica",
        "numero" : "1"
      }, {
        "horario" : "9.15 / 10.40",
        "id" : "Lengua",
        "numero" : "2"
      }, {
        "horario" : "10.50 / 12.15",
        "id" : "Matematica",
        "numero" : "3"
      }, {
        "horario" : "13.10 / 14.30",
        "id" : "Historia Judia",
        "numero" : "4"
      } ],
      "martes" : [ null, {
        "horario" : "7.45 / 9.05",
        "id" : "Analógica",
        "numero" : "1"
      }, {
        "horario" : "9.15 / 10.40",
        "id" : "Sistemas",
        "numero" : "2"
      }, {
        "horario" : "10.50 / 12.15",
        "id" : "Sistemas",
        "numero" : "3"
      }, {
        "horario" : "13.10 / 14.30",
        "id" : "Digitales",
        "numero" : "4"
      }, {
        "horario" : "14.40 / 16.00",
        "id" : "Digitales",
        "numero" : "5"
      }, {
        "horario" : "16.10 / 17.30",
        "id" : "Ingles",
        "numero" : "6"
      } ],
      "miercoles" : [ null, {
        "horario" : "7.45 / 9.05",
        "id" : "Analógica",
        "numero" : "1"
      }, {
        "horario" : "9.15 / 10.40",
        "id" : "Quimica",
        "numero" : "2"
      }, {
        "horario" : "10.50 / 12.15",
        "id" : "Historia Judia",
        "numero" : "3"
      }, {
        "horario" : "13.10 / 14.30",
        "id" : "Matematica",
        "numero" : "4"
      }, {
        "horario" : "14.40 / 16.00",
        "id" : "Ingles",
        "numero" : "5"
      }, {
        "horario" : "16.10 / 17.30",
        "id" : "Lengua",
        "numero" : "6"
      } ],
      "viernes" : [ null, {
        "horario" : "7.45 / 9.05",
        "id" : "PF",
        "numero" : "1"
      }, {
        "horario" : "9.15 / 10.40",
        "id" : "PF",
        "numero" : "2"
      }, {
        "horario" : "7.45 / 9.05",
        "id" : "PF",
        "numero" : "3"
      } ]
    }
  },
  "inasistencias" : {
    "5MA" : {
      "Analógica" : {
        "17sep" : {
          "ausentes" : {
            "43626546" : "Luciano Garbarino",
            "43725334" : "Dan Farach",
            "43917960" : "Dan Szujatovich",
            "43992906" : "Gianfranco Loayza",
            "44159126" : "Leonel Braginski"
          },
          "presentes" : {
            "44159126" : {
              "alumno" : "Leonel Braginski",
              "dni" : "44159126",
              "horario" : "20:53:08"
            }
          }
        }
      },
      "Digitales" : {
        "24sep" : {
          "ausentes" : {
            "43626546" : "Luciano_Garbarino",
            "43725334" : "Dan_Farach",
            "43917960" : "Dan_Szujatovich",
            "43992906" : "Gianfranco_Loayza"
          },
          "presentes" : {
            "43448452" : {
              "alumno" : "Andrés Guinsburg",
              "dni" : "43448452",
              "horario" : "15:48:07"
            },
            "43819469" : {
              "alumno" : "Tomas  Jais",
              "dni" : "43819469",
              "horario" : "15:30:05"
            },
            "44159126" : {
              "alumno" : "Leonel Braginski",
              "dni" : "44159126",
              "horario" : "15:48:53"
            }
          }
        }
      },
      "Filosofia" : {
        "5sep" : {
          "presentes" : {
            "44159126" : {
              "alumno" : "Leonel Braginski",
              "dni" : "44159126",
              "horario" : "17:06:14"
            }
          }
        }
      },
      "Fuentes" : {
        "5sep" : {
          "presentes" : {
            "44159126" : {
              "alumno" : "Leonel Braginski",
              "dni" : "44159126",
              "horario" : "14:31:37"
            }
          }
        }
      },
      "HRC" : {
        "20sep" : {
          "ausentes" : {
            "43626546" : "Luciano_Garbarino",
            "43725334" : "Dan_Farach",
            "43917960" : "Dan_Szujatovich",
            "43992906" : "Gianfranco_Loayza",
            "44159126" : "Leonel_Braginski"
          }
        }
      },
      "PF" : {
        "20sep" : {
          "ausentes" : {
            "43626546" : "Luciano_Garbarino",
            "43725334" : "Dan_Farach",
            "43917960" : "Dan_Szujatovich",
            "43992906" : "Gianfranco_Loayza",
            "44159126" : "Leonel_Braginski"
          },
          "presentes" : {
            "43725334" : {
              "alumno" : "Dan Farach",
              "dni" : "43725334",
              "horario" : "10:08:54"
            },
            "43917960" : {
              "alumno" : "Dan Szujatovich",
              "dni" : "43917960",
              "horario" : "10:07:51"
            },
            "43992906" : {
              "alumno" : "Gianfranco Loayza",
              "dni" : "43992906",
              "horario" : "10:10:15"
            },
            "44159126" : {
              "alumno" : "Leonel Braginski",
              "dni" : "44159126",
              "horario" : "11:12:12"
            }
          }
        },
        "30ago" : {
          "presentes" : {
            "43725334" : {
              "alumno" : "Dan Farach",
              "dni" : "43725334",
              "horario" : "09:00:50"
            },
            "43917960" : {
              "alumno" : "Dan Szujatovich",
              "dni" : "43917960",
              "horario" : "08:00:20"
            },
            "44159126" : {
              "alumno" : "Leonel Braginski",
              "dni" : "44159126",
              "horario" : "08:20:35"
            }
          }
        },
        "6sep" : {
          "presentes" : {
            "43626546" : {
              "alumno" : "Luciano Garbino",
              "dni" : "43626546",
              "horario" : "08:10:02"
            },
            "44159126" : {
              "alumno" : "Leonel Braginski",
              "dni" : "44159126",
              "horario" : "08:10:59"
            }
          }
        }
      },
      "PP" : {
        "22sep" : {
          "ausentes" : {
            "43626546" : "Luciano_Garbarino",
            "43725334" : "Dan_Farach",
            "43917960" : "Dan_Szujatovich",
            "43992906" : "Gianfranco_Loayza",
            "44159126" : "Leonel_Braginski"
          }
        },
        "26sep" : {
          "ausentes" : {
            "43448452" : "Andrés_Guinsburg",
            "43626546" : "Luciano_Garbarino",
            "43725334" : "Dan_Farach",
            "43819469" : "Tomas_Jais",
            "43917960" : "Dan_Szujatovich",
            "43992906" : "Gianfranco_Loayza",
            "44159126" : "Leonel_Braginski"
          },
          "presentes" : {
            "43630178" : {
              "alumno" : "Federico Custeau",
              "dni" : "43630178",
              "horario" : "10:16:10"
            },
            "44159126" : {
              "alumno" : "Leonel Braginski",
              "dni" : "44159126",
              "horario" : "10:06:58"
            }
          }
        }
      },
      "Sistemas" : {
        "17sep" : {
          "ausentes" : {
            "43626546" : "Luciano Garbarino",
            "43725334" : "Dan Farach",
            "43917960" : "Dan Szujatovich",
            "43992906" : "Gianfranco Loayza",
            "44159126" : "Leonel Braginski"
          }
        },
        "20sep" : {
          "ausentes" : {
            "43626546" : "Luciano_Garbarino",
            "43725334" : "Dan_Farach",
            "43917960" : "Dan_Szujatovich",
            "43992906" : "Gianfranco_Loayza",
            "44159126" : "Leonel_Braginski"
          }
        }
      }
    }
  },
  "qrs" : {
    "numeros" : "124118684"
  },
  "usuarios" : {
    "43448188" : {
      "dni" : "43448188",
      "email" : "",
      "nombre" : "Luciana Skakovsky",
      "password" : "luli01",
      "school" : "5MA"
    },
    "43448452" : {
      "dni" : "43448452",
      "email" : "",
      "nombre" : "Andrés Guinsburg",
      "password" : "andicapo",
      "school" : "5MA"
    },
    "43626546" : {
      "dni" : "43626546",
      "email" : "lucigar01@gmail.com",
      "nombre" : "Luciano Garbino",
      "password" : "lucho01",
      "school" : "5MA"
    },
    "43630178" : {
      "dni" : "43630178",
      "email" : "federicocus2015@gmail.com",
      "nombre" : "Federico Custeau",
      "password" : "fedecus19",
      "school" : "5MA"
    },
    "43697812" : {
      "dni" : "43697812",
      "email" : "mateo.enero30@gmail.com",
      "nombre" : "Mateo Stefanides",
      "password" : "mateo123",
      "school" : "5MA"
    },
    "43725334" : {
      "dni" : "43725334",
      "email" : "danfarach18@gmail.com",
      "nombre" : "Dan Farach",
      "password" : "5",
      "school" : "5MA"
    },
    "43819134" : {
      "dni" : "43819134",
      "email" : "",
      "nombre" : "Kevin Liao",
      "password" : "chino",
      "school" : "5MA"
    },
    "43819469" : {
      "dni" : "43819469",
      "email" : "tomijais@gmail.com",
      "nombre" : "Tomas Jais",
      "password" : "hola123",
      "school" : "5MA"
    },
    "43874249" : {
      "dni" : "43874249",
      "email" : "",
      "nombre" : "Federico Galante",
      "password" : "FedeXX",
      "school" : "5MA"
    },
    "43901510" : {
      "dni" : "43901510",
      "email" : "dinamitaestray@gmail.com",
      "nombre" : "Maximo Estray",
      "password" : "LEO123",
      "school" : "5MA"
    },
    "43917960" : {
      "dni" : "43917960",
      "email" : "",
      "nombre" : "Dan Szujatovich",
      "password" : "18",
      "school" : "5MA"
    },
    "43987841" : {
      "dni" : "43987841",
      "email" : "",
      "nombre" : "Milena Kuzminski Sabato",
      "password" : "holaleo",
      "school" : "5MA"
    },
    "43992906" : {
      "dni" : "43992906",
      "email" : "gianfrancozapata944@gmail.com",
      "nombre" : "Gianfranco Loayza",
      "password" : "perro123",
      "school" : "5MA"
    },
    "44159009" : {
      "dni" : "44159009",
      "email" : "marcos.sk8.parengo@gmail.com",
      "nombre" : "Marcos Parengo",
      "password" : "marcosmarcos",
      "school" : "5MA"
    },
    "44159126" : {
      "dni" : "44159126",
      "email" : "leobraginski@gmail.com",
      "nombre" : "Leonel Braginski",
      "password" : "oliver",
      "school" : "5MA"
    }
  }
}
